<?xml version="1.0" encoding="iso-8859-1"?>
<?xml-stylesheet type="text/xsl" href="h\estilo.xsl"?>

<documento		xmlns="http://www.ii.unam.mx"
				xmlns:xsi="http://www.w3.org/2001/XMLSchema-instance"
				xsi:schemaLocation="http://www.ii.unam.mx 
				h\esquema.xsd">
				
<encabezado id="115" permisos="todos">

	<titulo>N024608ESM07</titulo>
	<descripcion></descripcion>

	<parametros		generoLiterario="prosa" registro="estándar">
		<corpus><CEELE	zonaGeografica="Nayarit" areaTematica="no específica"/></corpus>
	</parametros>
	
	<hablante id="MUNPERCRI"/>

	<referencia id="MUNPERCRI">
		<lugar>Nayarit</lugar>
		<fechaOriginal>2010</fechaOriginal>
	</referencia>
	<responsables>
		<transcriptor nombres="" apellidos="" fecha=""></transcriptor>
		<etiquetador nombres="Argentina" apellidos="Robledo Domínguez" fecha="2010"/>
		<revisor nombres="" apellidos="" fecha=""/>
	</responsables>				
	
	<archivo nombre="N024608ESM07.txt"/>
	<imagen archivo="N024608ESM07.jpg"/>
	<vista tipo="T"/>
</encabezado>

<cuerpo>
<nl num="1"/><g n="Cristian">cristian<sus tipo="Cxc"/></g><e/>
<g>Isidro<mayNP/></g><e/>
<g>Mundo<mayNP/></g><e/>
<g n="Pérez">Perez<mayNP/><omi tipo="acento"/></g><l/>
<nl num="2"/><g>mi</g>
<g>escuela<hiposeg/></g><l/>
<nl num="3"/><pi><g n="Quién">Quien<mayIni/><omi tipo="acento"/></g><e/>
<g>soy</g><e/></pi>
<g n="Julián"><tachado>J</tachado><correccion tipo="susti"/>uLian<mayNP/><mayInter/><omi tipo="acento"/></g><e/>
<g>tengo</g><e/>
<g>mu<tachado>c</tachado><correccion tipo="susti"/>hos</g><e/>
<g  n="hermanos">hermano<omi tipo="s"/></g><e/>
<g>tengo</g><e/>
<g>7</g><e/>
<g n="años">año<omi tipo="s"/></g><l/>
<nl num="4"/><pi></pi><g n="cómo">como<omi tipo="acento"/></g><e/>
<g>es</g><e/>
<g n="nuestra"><tachado>n</tachado><correccion tipo="susti"/>ue<tachado>tra</tachado><correccion tipo="susti"/><omi tipo="s"/></g><e/>
<g n="escuela">escueLa<mayInter/></g><l/>
<nl num="5"/><g>se</g><e/>
<g>llama</g><e/>
<g n="Inés">ines<sus tipo="Ixi"/><omi tipo="acento"/></g><e/>
<g>de</g>
<g>la<hiposeg/></g><e/>
<g n="Cruz">grus<sus tipo="Cxg"/><sus tipo="zxs"/></g><e/>
<g>tiene</g><e/>
<g>much<tachado>o</tachado><correccion tipo="susti"/>s</g><e/>
<g n="salones">saLunes<mayInter/><sus tipo="oxu"/></g><e/>
<g>tiene</g>
<g>una<hiposeg/></g>
<g n="cancha">ca<tachado>n</tachado><correccion tipo="susti"/></g><l tipo="compac"/><l/>
<nl num="6"/><g>tiene</g><e/>
<g n="tiendita">tiendyta<sus tipo="ixy"/></g><e/>
<g>tiene</g><e/>
<g n="ventiladores">be<tachado>n</tachado><correccion tipo="susti"/>tiLad<tachado>o</tachado><correccion tipo="susti"/>res<sus tipo="vxb"/><mayInter/></g><l/>
<nl num="7"/><pi><g n="Cómo">como<omi tipo="acento"/><sus tipo="Cxc"/></g><e/>
<g><tachado>ll</tachado><correccion tipo="susti"/>egamos</g><e/>
<g>a</g><e/>
<g n="la">La<sus tipo="lxL"/></g><e/>
<g n="escuela">escueLa<mayInter/></g><l/></pi>
<nl num="8"/><g>en</g><e/>
<g n="bicicleta">bisicleta<sus tipo="cxs"/></g><e/>
<g n="a">am<agre tipo="m"/></g>
<g n="veces">bese<sus tipo="vxb"/><sus tipo="cxs"/><omi tipo="s"/><hiposeg/></g><e/>
<g>me</g><e/>
<g n="trae">tr<tachado>a</tachado><correccion tipo="susti"/>i<sus tipo="exi"/></g><e/>
<g>mi</g><e/>
<g n="papá">papa<omi tipo="acento"/></g><l/>
<nl num="9"/><pi><g n="Qué">Que<omi tipo="acento"/></g><e/>
<g n="aprendemos">prendemos<omi tipo="a" error="concord"/></g><e/>
<g>en</g><e/>
<g>la</g><e/>
<g>escuela</g><l/></pi>
<nl num="10"/><g n="Yo">yo<sus tipo="Yxy"/></g><e/>
<g n="aprendo">prendo<omi tipo="a" error="concord"/></g><e/>
<g>a</g><e/>
<g n="la">La<sus tipo="lxL"/></g><e/>
<g>cuentas</g><l/>
<nl num="11"/><g>y</g><e/>
<g>a</g>
<g n="la">La<sus tipo="lxL"/></g><e/>
<g n="tablas"><tachado>X</tachado><correccion tipo="susti"/>tablas</g><l/>
<l/>
</cuerpo>
<comentarios>
<com>3. encima "J", encima "c" sobre "e"</com>
<com>4. encima "n" sobre "m", encima "tra"</com>
<com>5. encima "o" sobre "a", encima "n"</com>
<com>6. encima "n" sobre "m", encima "o" sobre "a"</com>
<com>7. encima "ll"</com>
<com>8. encima "i" sobre "a"</com>
<com>11.tacha lo que escribe</com>
</comentarios>
</documento>