<?xml version="1.0" encoding="iso-8859-1"?>
<?xml-stylesheet type="text/xsl" href="h\estilo.xsl"?>

<documento		xmlns="http://www.ii.unam.mx"
				xmlns:xsi="http://www.w3.org/2001/XMLSchema-instance"
				xsi:schemaLocation="http://www.ii.unam.mx 
				h\esquema.xsd">
				
<encabezado id="150" permisos="todos">

	<titulo>N040401ESM37</titulo>
	<descripcion></descripcion>

	<parametros		generoLiterario="prosa" registro="estándar">
		<corpus><CEELE	zonaGeografica="Nayarit" areaTematica="no específica"/></corpus>
	</parametros>
	
	<hablante id="RODPAZJOS"/>

	<referencia id="RODPAZJOS">
		<lugar>Nayarit</lugar>
		<fechaOriginal>2010</fechaOriginal>
	</referencia>
	<responsables>
		<transcriptor nombres="" apellidos="" fecha=""></transcriptor>
		<etiquetador nombres="María" apellidos="Pucci" fecha="2010"/>
		<revisor nombres="" apellidos="" fecha=""/>
	</responsables>				

	<archivo nombre="N040401ESM37.txt"/>
	<imagen archivo="N040401ESM37.jpg"/>
	<vista tipo="T"/>	
</encabezado>
<cuerpo>
<nl num="1"/><pi><g n="Quién">Q<mayIni/>uie<omi tipo="acento"/>n</g><e/>
<g><tachado>soy</tachado><correccion tipo="susti"/></g></pi><e/>
<e/>
<g>R<mayNP/>odrigo</g><e/>
<g n="Rodríguez"><tachado>R<mayNP/>odri<omi tipo="acento"/>guez</tachado><correccion tipo="susti"/></g><e/>
<g n="de">D<sus tipo="dxD"/>e</g><e/>
<g n="la">L<sus tipo="lxL"/>a</g><l/>
<nl num="2"/><g>mi</g><e/>
<g n="escuela">escueL<mayInter/>a</g><e/>
<g>se</g><e/>
<g n="llama"><tachado>y<sus tipo="llxy"/>o<sus tipo="axo"/>ma</tachado><correccion tipo="susti"/></g><e/>
<g n="Escuela"><tachado>E<mayNP/>scueL<mayInter/>a</tachado><correccion tipo="susti"/></g><e/>
<g>R<mayNP/>afael</g><e/>
<g n="Ramírez">R<mayNP/>ami<omi tipo="acento"/>R<mayInter/><omi tipo="e"/><omi tipo="z"/></g><l/>
<nl num="3"/><g>mi</g><e/>
<r c="Fia">¿</r><e/>
<g n="escuela">escueL<mayInter/>a</g><e/>
<r c="Fit">?<agre tipo="?"/></r><e/>
<g>tiene</g><e/>
<g n="salón"><tachado>z<sus tipo="sxz"/></tachado><correccion tipo="susti"/>alon<omi tipo="acento"/></g><e/>
<pi><g n="Cómo">c<sus tipo="Cxc"/>o<omi tipo="acento"/>mo</g><e/>
<g n="llegamos">y<sus tipo="llxy"/>egamos</g></pi><l/>
<nl num="4"/><g>a</g><e/>
<g n="las">L<sus tipo="lxL"/>as</g><e/>
<g>7</g><e/>
<g n="y">i<sus tipo="yxi"/><hiposeg/></g><g>media</g><e/>
<g>mi</g><e/>
<g>papá</g><e/>
<g>me</g><e/>
<g n="trae">trai<sus tipo="exi"/></g><l/>
<nl num="5"/><g>mi</g><e/>
<g>papá</g><e/>
<pi><g n="Qué">que<omi tipo="acento"/></g><e/>
<g n="hacemos"><omi tipo="h"/><omi tipo="a"/>s<sus tipo="cxs"/>es<agre tipo="s"/>mos</g><e/>
<g><tachado>en</tachado><correccion tipo="susti"/></g><e/>
<nl num="6"/><g>en</g><e/>
<g n="escuela">escueL<mayInter/>a</g></pi><e/>
<g>trabajo</g><e/>
<g>y</g><e/>
<g>escribo</g><e/>
<g>y<hiposeg/></g><g>pa</g><l/>
<l/>
<nl num="7"/><g>el</g><e/>
<g tipo="fecha" n="noviembre del año 2005">N<sus tipo="nxN"/>ob<sus tipo="vxb"/>iembre<e/>
del<e/>
año<e/>
2005</g><l/>
<l/>
</cuerpo>
<comentarios>
<com>1, 2. Borra y escribe encima</com>
<com>3, 5. Encima y escribe encima</com>
<com>7. Borra</com>
<com>Entre 6 y 7. Dibuja una línea entre el texto y la fecha</com>
<com>Hace guiones largos luego de cada bloque temático marcado por preguntas.</com>
</comentarios>
</documento>