<?xml version="1.0" encoding="iso-8859-1"?>
<?xml-stylesheet type="text/xsl" href="h\estilo.xsl"?>

<documento		xmlns="http://www.ii.unam.mx"
				xmlns:xsi="http://www.w3.org/2001/XMLSchema-instance"
				xsi:schemaLocation="http://www.ii.unam.mx 
				h\esquema.xsd">
				
<encabezado id="82" permisos="todos">
	<titulo>S040404ESF49</titulo>
	<descripcion></descripcion>

	<parametros		generoLiterario="prosa" registro="estándar">
		<corpus><CEELE	zonaGeografica="Nayarit" areaTematica="no específica"/></corpus>
	</parametros>
	
	<hablante id="ALCHERAND"/>

	<referencia id="ALCHERAND">
		<lugar>Nayarit</lugar>
		<fechaOriginal>2010</fechaOriginal>
	</referencia>
	<responsables>
		<transcriptor nombres="" apellidos="" fecha=""></transcriptor>
		<etiquetador nombres="María" apellidos="Pucci" fecha="2010"/>
		<revisor nombres="" apellidos="" fecha=""/>
	</responsables>	

	<archivo nombre="S040404ESF49.txt"/>
	<imagen archivo="S040404ESF49A.jpg"/>
	<imagen archivo="S040404ESF49B.jpg"/>
	<vista tipo="T"/>
</encabezado>

<cuerpo>
<nl num="1"/><g>m<agrandaMin/><mayIni/>i</g><e/>
<g n="escuela">E<sus tipo="exE"/>S<mayInter/>cuela</g><e/>
<l/>
<l/>
<nl num="2"/><g>H<mayIni/>ola</g><e/>
<g n="Fátima">F<mayNP/>a<omi tipo="acento"/>tima</g><e/>
<g>soy</g><e/>
<g>A<mayNP/>ndrea</g><e/>
<g>B<mayNP/>eatriz</g><e/>
<g>A<mayNP/>lcantar</g><e/>
<g tipo="abrev" n="H.">H<r c="Fg">-</r><sus tipo="punto abrev x guión"/></g><e/>
<l/>
<nl num="3"/><g>mi</g><e/>
<g>escuela</g><e/>
<g>se</g><e/>
<g>llama</g><e/>
<g tipo="abrev" n="Gral.">G<mayNP/>ral<r c="Fd">:<sus tipo="punto abr x dos puntos"/></r></g><e/>
<g>J<mayNP/>uventino<hiposeg/></g><g>E<mayNP/>spinosa</g><l/>
<l/>
<nl num="4"/><g>yo</g><e/>
<g>soy</g><e/>
<g>del</g><e/>
<g n="país">P<sus tipo="pxP"/>ai<omi tipo="acento"/>s</g><e/>
<g>M<mayNP/>éxico</g><e/>
<g>y</g><e/>
<g>mis</g><e/>
<l/>
<nl num="5"/><g>papás</g><e/>
<g>se</g><e/>
<g>llaman</g><e/>
<g>E<mayNP/>duardo</g><e/>
<g n="Hernández">H<mayNP/>é<per tipo="acento"/>rnandez</g><l/>
<nl num="6"/><g n="González">G<mayNP/>ons<sus tipo="zxs"/>a<omi tipo="acento"/>les<sus tipo="zxs"/></g><e/>
<g>mi<hiposeg/></g><g n="mamá">mama<omi tipo="acento"/></g><e/>
<g>se</g><e/>
<g>llama</g><l/>
<nl num="7"/><g>B<mayNP/>eatriz</g><e/>
<g><tachado>Alco</tachado><correccion tipo="elimi"/></g><e/>
<g n="Hernández">H<mayNP/>é<per tipo="acento"/>rnandez</g><e/>
<g n="Martínez">m<sus tipo="Mxm"/>arti<omi tipo="acento"/>nes<sus tipo="zxs"/></g><l/>
<nl num="8"/><g>tu</g><e/>
<g n="país">P<sus tipo="pxP"/>ai<omi tipo="acento"/>s</g><e/>
<g>es</g><e/>
<g>soleado</g><e/>
<g>el</g><e/>
<g n="mío">mi<omi tipo="acento"/>o</g><e/>
<g>es</g><e/>
<g>un</g><e/>
<g n="poco">P<sus tipo="pxP"/>oco</g><l/>
<nl num="9"/><g n="caluroso">calo<sus tipo="uxo"/>roso</g><e/>
<g n="yo">Y<sus tipo="yxY"/>o</g><e/>
<g>A<mayNP/>ndrea</g><e/>
<g>tengo</g><e/>
<g><tachado>X</tachado><correccion tipo="elimi"/></g><e/><g>7</g><e/>
<g>años</g><l/>
<nl num="10"/><g>mi<hiposeg/></g><g>escuela</g><e/>
<e/>
<g>es</g><e/>
<g>de</g><e/>
<g n="ladrillos">ladri<tachado>yos</tachado><correccion tipo="susti"/><sus tipo="llxy"/></g><e/>
<g><tachado>y</tachado></g><e/>
<g><tachado>mis</tachado></g><e/>
<g><tachado>amigos</tachado><correccion tipo="elimi"/></g><l/>
<nl num="11"/><g>son</g><e/>
<g>de</g><e/>
<g>colores</g><e/>
<g>muy</g><e/>
<g>bonitos</g><e/>
<g>yo<hiposeg/></g><g>en<hiposeg/></g><g>mi</g><e/>
<g n="salón">sá<per tipo="acento"/>lon</g><l/>
<nl num="12"/><g>tengo</g><e/>
<g>tele</g><e/>
<g n="pintarrón">P<sus tipo="pxP"/>intarro<omi tipo="acento"/>n</g><e/>
<g>tenemos</g><e/>
<g n="dirección">D<sus tipo="dxD"/>ireccio<omi tipo="acento"/>n</g><e/>
<l/>
<nl num="13"/><g n="aquí">h<agre tipo="h"/>a<tachado>qu</tachado><correccion tipo="susti"/>i<omi tipo="acento"/></g><e/>
<g>es</g><e/>
<g>una</g><e/>
<g n="escuela">E<sus tipo="exE"/>scuela</g><e/>
<g tipo="otra" n="aprendisada">A<sus tipo="axA"/>P<mayInter/>rendisada</g><l/>
<nl num="14"/><g>y</g><e/>
<g n="aprendemos">A<sus tipo="axA"/>P<mayInter/>rendemos</g><e/>
<g>mucho</g><e/>
<g n="tú">tu<omi tipo="acento"/></g><e/>
<g n="también">tambie<omi tipo="acento"/>n<hiposeg/></g><g>tu</g><e/>
<l/>
<nl num="15"/><g>salón</g><e/>
<g>es</g><e/>
<g>de</g><e/>
<g>paja<hiposeg/></g><g>nos</g><e/>
<g>dan</g><e/><g>clases</g><e/><g>de</g><e/>
<l/>
<nl num="16"/><g>computación</g><e/>
<l/>
<l/>
<nl num="17"/><g n="venden">V<sus tipo="vxV"/>enden</g><e/>
<g n="pizzas">P<sus tipo="pxP"/>izzas</g><e/>
<g n="también">tambie<omi tipo="acento"/>n</g><e/>
<g><tachado>m</tachado><correccion tipo="elimi"/></g><e/>
<g>nos</g><e/>
<l/>
<nl num="18"/><g>dan</g><e/>
<g>clases</g><e/>
<g>de</g><e/>
<g n="matemáticas">matema<omi tipo="acento"/>ticas</g><l/>
<nl num="19"/><pi><g n="cómo">co<omi tipo="acento"/>mo</g><e/>
<g>llegan</g><e/>
<g>a<hiposeg/></g><g>la</g><e/>
<g>escuela</g></pi><e/>
<g n="tú">tu<omi tipo="acento"/></g><e/>
<g>comes</g><l/>
<nl num="20"/><g>en</g><e/>
<g>la</g><e/>
<g n="escuela">E<sus tipo="exE"/>scuela</g><e/>
<g>mi</g><e/>
<g>mamá</g><e/>
<g>me</g><e/>
<g n="trae">tray<sus tipo="exy"/></g><e/>
<g>a</g><e/>
<g>la</g><e/>
<l/>
<nl num="21"/><g>escuela</g><e/>
<g n="yo">Y<sus tipo="yxY"/>o</g><e/>
<g n="llevo">lleb<sus tipo="vxb"/>o</g><e/>
<g>lonche</g><l/>
<l/>
<nl num="22"/><g n="nosotros">no<e/><hiperseg/>sotros</g><e/>
<g>tenemos</g><e/>
<g><tachado>Libo</tachado><correccion tipo="elimi"/></g><e/>
<g n="libros">L<sus tipo="Lxl"/>ibros</g><l/>
<nl num="23"/><g n="tú">tu<omi tipo="acento"/></g><e/>
<g>los</g><e/>
<g>compras</g><e/>
<g><tachado>que</tachado><correccion tipo="elimi"/></g><e/><g n="cómo">co<omi tipo="acento"/>mo</g><e/>
<g n="escribes">E<sus tipo="exE"/>scribes</g><e/>
<l/>
<nl num="24"/><g>nosotros</g><e/>
<g n="Escribimos">E<sus tipo="exE"/>scribimos</g><e/>
<g>con</g><e/>
<g>cuadernos</g><e/>
<l/>
<nl num="25"/><g>nosotros</g><e/>
<g>comemos</g><e/>
<g>en</g><e/>
<g>el</g><e/>
<g n="piso">pis<omi tipo="o"/></g><e/>
<g n="a">A<sus tipo="axA"/></g><e/>
<g>ustedes</g><e/>
<l/>
<nl num="26"/><g>les</g><e/>
<g>dan</g><e/>
<g>de</g><e/>
<g>comer</g><e/>
<g>en</g><e/>
<g>la</g><e/>
<g>escuela</g><l/>
<nl num="27"/><g n="ustedes">ustede<tachado>X</tachado><correccion tipo="elimi"/><omi tipo="s"/></g><e/>
<g n="ustedes">U<sus tipo="uxU"/>S<mayInter/><tachado>t</tachado><correccion tipo="elimi"/>edes</g><e/>
<g>tienen</g><e/>
<g n="luz">L<sus tipo="lxL"/>uz</g><l/>
<nl num="28"/><g>no</g><e/>
<g>verdad</g><e/>
<g>nosotros</g><e/>
<g n="sí">si<omi tipo="acento"/></g><e/>
<g>tenemos</g><e/>
<g n="luz">L<sus tipo="lxL"/>uz</g><l/>
<nl num="29"/><g n="sus">S<sus tipo="sxS"/>o<sus tipo="uxo"/><omi tipo="s"/></g><e/>
<g n="maestros">maest<tachado>X</tachado><correccion tipo="elimi"/><omi tipo="r"/><omi tipo="o"/><omi tipo="s"/></g><e/>
<g>maestros</g><e/>
<g n="cómo">co<omi tipo="acento"/>mo</g><e/>
<g>se</g><e/>
<g>llaman</g><l/>
<nl num="30"/><g n="Luís">L<mayNP/>u<tachado>y</tachado><correccion tipo="elimi"/><omi tipo="i"/><omi tipo="acento"/><omi tipo="s"/></g><e/>
<g n="Luís">L<mayNP/>ui<omi tipo="s"/>s</g><e/>
<g>y</g><e/>
<g n="Fátima">P<sus tipo="FxP"/><mayNP/>a<omi tipo="acento"/>tima</g><e/>
<g n="adiós">A<sus tipo="axA"/>dio<omi tipo="acento"/>s</g><e/>
<g n="Fátima">f<agrandaMin/><mayNP/>a<omi tipo="acento"/>tima</g><e/>
<g>de</g><e/>
<l/>
<l/>
<nl num="31"/><firma tipo="b"><g>Andrea</g></firma><e/>
<l/>
<l/>
</cuerpo>
<comentarios>
<com>1 Agranda "m" de "mi" aparentar mayúscula</com>
<com>2 Le hace puntos a la "H"</com>
<com>7 Tacha</com>
<com>9 Tacha</com>
<com>10 Encima</com>
<com>10 Tacha</com>
<com>13 Hace punto a la "u" </com>
<com>17 Tacha</com>
<com>22 Tacha</com>
<com>23 Tacha</com>
<com>27 Tacha</com>
<com>27 Encima</com>
<com>29 Tacha</com>
<com>30 Tacha</com>
<com>31 Firma: Escribe sun nombre con letra grande</com>
<com>Diseño de página: Firma centrada</com>

</comentarios>
</documento>